{
  "center": 17255,
  "nodes": [
    {
      "id": 76,
      "name": "Ming Ren",
      "type": "Person",
      "genre": null,
      "release_date": null,
      "notable": null,
      "depth": 3
    },
    {
      "id": 304,
      "name": "Belinda Knappe",
      "type": "Person",
      "genre": null,
      "release_date": null,
      "notable": null,
      "depth": 3
    },
    {
      "id": 455,
      "name": "Yang Peng",
      "type": "Person",
      "genre": null,
      "release_date": null,
      "notable": null,
      "depth": 3
    },
    {
      "id": 457,
      "name": "Min Cao",
      "type": "Person",
      "genre": null,
      "release_date": null,
      "notable": null,
      "depth": 3
    },
    {
      "id": 876,
      "name": "Bold Without Apology",
      "type": "Song",
      "genre": "Indie Rock",
      "release_date": "2010",
      "notable": true,
      "depth": 2
    },
    {
      "id": 877,
      "name": "Qiang Zhou",
      "type": "Person",
      "genre": null,
      "release_date": null,
      "notable": null,
      "depth": 3
    },
    {
      "id": 878,
      "name": "Jing Kang",
      "type": "Person",
      "genre": null,
      "release_date": null,
      "notable": null,
      "depth": 3
    },
    {
      "id": 934,
      "name": "Jun Zhou",
      "type": "Person",
      "genre": null,
      "release_date": null,
      "notable": null,
      "depth": 3
    },
    {
      "id": 1276,
      "name": "Yong Dong",
      "type": "Person",
      "genre": null,
      "release_date": null,
      "notable": null,
      "depth": 3
    },
    {
      "id": 1294,
      "name": "Urszula Stochmal",
      "type": "Person",
      "genre": null,
      "release_date": null,
      "notable": null,
      "depth": 3
    },
    {
      "id": 1335,
      "name": "Ming Long",
      "type": "Person",
      "genre": null,
      "release_date": null,
      "notable": null,
      "depth": 3
    },
    {
      "id": 1336,
      "name": "Yong Lu",
      "type": "Person",
      "genre": null,
      "release_date": null,
      "notable": null,
      "depth": 3
    },
    {
      "id": 1952,
      "name": "Yang Wan",
      "type": "Person",
      "genre": null,
      "release_date": null,
      "notable": null,
      "depth": 3
    },
    {
      "id": 2197,
      "name": "Hallowed Transaction",
      "type": "Album",
      "genre": "Doom Metal",
      "release_date": "2017",
      "notable": true,
      "depth": 2
    },
    {
      "id": 2198,
      "name": "Yoko Hashimoto",
      "type": "Person",
      "genre": null,
      "release_date": null,
      "notable": null,
      "depth": 3
    },
    {
      "id": 2199,
      "name": "Kaori Ito",
      "type": "Person",
      "genre": null,
      "release_date": null,
      "notable": null,
      "depth": 3
    },
    {
      "id": 2200,
      "name": "Naoko Sato",
      "type": "Person",
      "genre": null,
      "release_date": null,
      "notable": null,
      "depth": 3
    },
    {
      "id": 2400,
      "name": "Yan Tang",
      "type": "Person",
      "genre": null,
      "release_date": null,
      "notable": null,
      "depth": 3
    },
    {
      "id": 2705,
      "name": "Jeremiah Love",
      "type": "Person",
      "genre": null,
      "release_date": null,
      "notable": null,
      "depth": 3
    },
    {
      "id": 2706,
      "name": "Zachary Francis",
      "type": "Person",
      "genre": null,
      "release_date": null,
      "notable": null,
      "depth": 3
    },
    {
      "id": 2707,
      "name": "Robert Woods",
      "type": "Person",
      "genre": null,
      "release_date": null,
      "notable": null,
      "depth": 3
    },
    {
      "id": 3086,
      "name": "Sean Jones",
      "type": "Person",
      "genre": null,
      "release_date": null,
      "notable": null,
      "depth": 3
    },
    {
      "id": 3760,
      "name": "Min Long",
      "type": "Person",
      "genre": null,
      "release_date": null,
      "notable": null,
      "depth": 3
    },
    {
      "id": 3761,
      "name": "Gang Shao",
      "type": "Person",
      "genre": null,
      "release_date": null,
      "notable": null,
      "depth": 3
    },
    {
      "id": 3763,
      "name": "Qiang Yuan",
      "type": "Person",
      "genre": null,
      "release_date": null,
      "notable": null,
      "depth": 3
    },
    {
      "id": 3764,
      "name": "Wei Zhao",
      "type": "Person",
      "genre": null,
      "release_date": null,
      "notable": null,
      "depth": 3
    },
    {
      "id": 3881,
      "name": "Susurros de Pasi\u00f3n",
      "type": "Song",
      "genre": "Synthwave",
      "release_date": "2004",
      "notable": true,
      "depth": 2
    },
    {
      "id": 3882,
      "name": "Juan Zhou",
      "type": "Person",
      "genre": null,
      "release_date": null,
      "notable": null,
      "depth": 3
    },
    {
      "id": 3883,
      "name": "Yang Zhao",
      "type": "Person",
      "genre": null,
      "release_date": null,
      "notable": null,
      "depth": 3
    },
    {
      "id": 3986,
      "name": "Altitude of Mistakes",
      "type": "Song",
      "genre": "Americana",
      "release_date": "2015",
      "notable": true,
      "depth": 2
    },
    {
      "id": 3987,
      "name": "Xiulan Fang",
      "type": "Person",
      "genre": null,
      "release_date": null,
      "notable": null,
      "depth": 3
    },
    {
      "id": 3988,
      "name": "Qiang Liu",
      "type": "Person",
      "genre": null,
      "release_date": null,
      "notable": null,
      "depth": 3
    },
    {
      "id": 3989,
      "name": "Jun Qiao",
      "type": "Person",
      "genre": null,
      "release_date": null,
      "notable": null,
      "depth": 3
    },
    {
      "id": 3990,
      "name": "Ming Huang",
      "type": "Person",
      "genre": null,
      "release_date": null,
      "notable": null,
      "depth": 3
    },
    {
      "id": 5213,
      "name": "Samantha Bullock",
      "type": "Person",
      "genre": null,
      "release_date": null,
      "notable": null,
      "depth": 3
    },
    {
      "id": 5574,
      "name": "Our Inevitable Path",
      "type": "Song",
      "genre": "Indie Folk",
      "release_date": "2017",
      "notable": true,
      "depth": 2
    },
    {
      "id": 5575,
      "name": "Shannon Harvey",
      "type": "Person",
      "genre": null,
      "release_date": null,
      "notable": null,
      "depth": 3
    },
    {
      "id": 6592,
      "name": "When the Bar Lights Go Up",
      "type": "Song",
      "genre": "Emo/Pop Punk",
      "release_date": "2000",
      "notable": true,
      "depth": 2
    },
    {
      "id": 6593,
      "name": "Lori Massey",
      "type": "Person",
      "genre": null,
      "release_date": null,
      "notable": null,
      "depth": 3
    },
    {
      "id": 7026,
      "name": "Reflejo Interior",
      "type": "Song",
      "genre": "Americana",
      "release_date": "1983",
      "notable": true,
      "depth": 2
    },
    {
      "id": 7027,
      "name": "Sheryl Roman",
      "type": "Person",
      "genre": null,
      "release_date": null,
      "notable": null,
      "depth": 3
    },
    {
      "id": 7028,
      "name": "John Graves",
      "type": "Person",
      "genre": null,
      "release_date": null,
      "notable": null,
      "depth": 3
    },
    {
      "id": 7029,
      "name": "Jason Aguirre",
      "type": "Person",
      "genre": null,
      "release_date": null,
      "notable": null,
      "depth": 3
    },
    {
      "id": 7030,
      "name": "Matthew Lane",
      "type": "Person",
      "genre": null,
      "release_date": null,
      "notable": null,
      "depth": 3
    },
    {
      "id": 8026,
      "name": "Cipriano Peranda",
      "type": "Person",
      "genre": null,
      "release_date": null,
      "notable": null,
      "depth": 3
    },
    {
      "id": 8207,
      "name": "Echoes of Forgotten Light",
      "type": "Song",
      "genre": "Alternative Rock",
      "release_date": "2004",
      "notable": true,
      "depth": 2
    },
    {
      "id": 8208,
      "name": "Igor Dy\u015b",
      "type": "Person",
      "genre": null,
      "release_date": null,
      "notable": null,
      "depth": 3
    },
    {
      "id": 8880,
      "name": "Tao Gao",
      "type": "Person",
      "genre": null,
      "release_date": null,
      "notable": null,
      "depth": 3
    },
    {
      "id": 9223,
      "name": "F\u00fcr uns alle zusammen",
      "type": "Song",
      "genre": "Alternative Rock",
      "release_date": "2017",
      "notable": true,
      "depth": 2
    },
    {
      "id": 9224,
      "name": "Joseph Ponce",
      "type": "Person",
      "genre": null,
      "release_date": null,
      "notable": null,
      "depth": 3
    },
    {
      "id": 9225,
      "name": "Herbert Mcfarland",
      "type": "Person",
      "genre": null,
      "release_date": null,
      "notable": null,
      "depth": 3
    },
    {
      "id": 9226,
      "name": "Rachel Montes",
      "type": "Person",
      "genre": null,
      "release_date": null,
      "notable": null,
      "depth": 3
    },
    {
      "id": 9227,
      "name": "Caitlin Miller",
      "type": "Person",
      "genre": null,
      "release_date": null,
      "notable": null,
      "depth": 3
    },
    {
      "id": 9228,
      "name": "Rebecca Wise",
      "type": "Person",
      "genre": null,
      "release_date": null,
      "notable": null,
      "depth": 3
    },
    {
      "id": 9848,
      "name": "Partisan's Lament",
      "type": "Song",
      "genre": "Indie Pop",
      "release_date": "2030",
      "notable": true,
      "depth": 2
    },
    {
      "id": 10016,
      "name": "Dreamscape of Judgment",
      "type": "Song",
      "genre": "Symphonic Metal",
      "release_date": "2023",
      "notable": true,
      "depth": 2
    },
    {
      "id": 10017,
      "name": "Ping Liao",
      "type": "Person",
      "genre": null,
      "release_date": null,
      "notable": null,
      "depth": 3
    },
    {
      "id": 10018,
      "name": "Trevor Bass",
      "type": "Person",
      "genre": null,
      "release_date": null,
      "notable": null,
      "depth": 3
    },
    {
      "id": 10019,
      "name": "Xiuying Du",
      "type": "Person",
      "genre": null,
      "release_date": null,
      "notable": null,
      "depth": 3
    },
    {
      "id": 10020,
      "name": "Xia Yuan",
      "type": "Person",
      "genre": null,
      "release_date": null,
      "notable": null,
      "depth": 3
    },
    {
      "id": 10021,
      "name": "Sandra Burke",
      "type": "Person",
      "genre": null,
      "release_date": null,
      "notable": null,
      "depth": 3
    },
    {
      "id": 10022,
      "name": "Yan Li",
      "type": "Person",
      "genre": null,
      "release_date": null,
      "notable": null,
      "depth": 3
    },
    {
      "id": 10534,
      "name": "Twelve Bells of Augsburg",
      "type": "Song",
      "genre": "Psychedelic Rock",
      "release_date": "2026",
      "notable": true,
      "depth": 2
    },
    {
      "id": 10903,
      "name": "Parallel Memories",
      "type": "Song",
      "genre": "Dream Pop",
      "release_date": "2028",
      "notable": true,
      "depth": 2
    },
    {
      "id": 10904,
      "name": "Ping Jin",
      "type": "Person",
      "genre": null,
      "release_date": null,
      "notable": null,
      "depth": 3
    },
    {
      "id": 10905,
      "name": "Tao Wen",
      "type": "Person",
      "genre": null,
      "release_date": null,
      "notable": null,
      "depth": 3
    },
    {
      "id": 10906,
      "name": "Guiying Ren",
      "type": "Person",
      "genre": null,
      "release_date": null,
      "notable": null,
      "depth": 3
    },
    {
      "id": 10907,
      "name": "Lei Shi",
      "type": "Person",
      "genre": null,
      "release_date": null,
      "notable": null,
      "depth": 3
    },
    {
      "id": 10908,
      "name": "Wei Liang",
      "type": "Person",
      "genre": null,
      "release_date": null,
      "notable": null,
      "depth": 3
    },
    {
      "id": 11254,
      "name": "Divergent Memories",
      "type": "Song",
      "genre": "Indie Folk",
      "release_date": "2017",
      "notable": true,
      "depth": 2
    },
    {
      "id": 11255,
      "name": "Joshua Taylor",
      "type": "Person",
      "genre": null,
      "release_date": null,
      "notable": null,
      "depth": 3
    },
    {
      "id": 12237,
      "name": "Provence Aria",
      "type": "Song",
      "genre": "Indie Rock",
      "release_date": "2023",
      "notable": true,
      "depth": 2
    },
    {
      "id": 12238,
      "name": "Lei Fu",
      "type": "Person",
      "genre": null,
      "release_date": null,
      "notable": null,
      "depth": 3
    },
    {
      "id": 12239,
      "name": "Yan Dai",
      "type": "Person",
      "genre": null,
      "release_date": null,
      "notable": null,
      "depth": 3
    },
    {
      "id": 12240,
      "name": "Daniel Mccormick",
      "type": "Person",
      "genre": null,
      "release_date": null,
      "notable": null,
      "depth": 3
    },
    {
      "id": 12241,
      "name": "Lei Jin",
      "type": "Person",
      "genre": null,
      "release_date": null,
      "notable": null,
      "depth": 3
    },
    {
      "id": 12685,
      "name": "Coastal Whispers of Biscay",
      "type": "Song",
      "genre": "Alternative Rock",
      "release_date": "2031",
      "notable": true,
      "depth": 2
    },
    {
      "id": 12686,
      "name": "James Medina",
      "type": "Person",
      "genre": null,
      "release_date": null,
      "notable": null,
      "depth": 3
    },
    {
      "id": 12687,
      "name": "Matthew Best",
      "type": "Person",
      "genre": null,
      "release_date": null,
      "notable": null,
      "depth": 3
    },
    {
      "id": 12688,
      "name": "Linda Burns",
      "type": "Person",
      "genre": null,
      "release_date": null,
      "notable": null,
      "depth": 3
    },
    {
      "id": 12948,
      "name": "Brooke Olson",
      "type": "Person",
      "genre": null,
      "release_date": null,
      "notable": null,
      "depth": 3
    },
    {
      "id": 13014,
      "name": "Exoskeleton Dissolve",
      "type": "Song",
      "genre": "Indie Rock",
      "release_date": "2020",
      "notable": true,
      "depth": 2
    },
    {
      "id": 13015,
      "name": "David Reese",
      "type": "Person",
      "genre": null,
      "release_date": null,
      "notable": null,
      "depth": 3
    },
    {
      "id": 13016,
      "name": "Ryan Dunlap",
      "type": "Person",
      "genre": null,
      "release_date": null,
      "notable": null,
      "depth": 3
    },
    {
      "id": 13017,
      "name": "Elmo Calbo",
      "type": "Person",
      "genre": null,
      "release_date": null,
      "notable": null,
      "depth": 3
    },
    {
      "id": 13018,
      "name": "Amico Luciani",
      "type": "Person",
      "genre": null,
      "release_date": null,
      "notable": null,
      "depth": 3
    },
    {
      "id": 13589,
      "name": "Silent Steps in the Forest's Embrace",
      "type": "Song",
      "genre": "Avant-Garde Folk",
      "release_date": "2023",
      "notable": true,
      "depth": 2
    },
    {
      "id": 13590,
      "name": "Wei Zhao",
      "type": "Person",
      "genre": null,
      "release_date": null,
      "notable": null,
      "depth": 3
    },
    {
      "id": 14107,
      "name": "Folklore's Heartbeat",
      "type": "Song",
      "genre": "Blues Rock",
      "release_date": "2020",
      "notable": true,
      "depth": 2
    },
    {
      "id": 14108,
      "name": "Tao Hu",
      "type": "Person",
      "genre": null,
      "release_date": null,
      "notable": null,
      "depth": 3
    },
    {
      "id": 14296,
      "name": "The Long Way Home",
      "type": "Album",
      "genre": "Dream Pop",
      "release_date": "2023",
      "notable": true,
      "depth": 2
    },
    {
      "id": 14297,
      "name": "Ming Qiao",
      "type": "Person",
      "genre": null,
      "release_date": null,
      "notable": null,
      "depth": 3
    },
    {
      "id": 14298,
      "name": "Na Ye",
      "type": "Person",
      "genre": null,
      "release_date": null,
      "notable": null,
      "depth": 3
    },
    {
      "id": 14352,
      "name": "Weathered Miles",
      "type": "Song",
      "genre": "Doom Metal",
      "release_date": "2023",
      "notable": true,
      "depth": 2
    },
    {
      "id": 14353,
      "name": "Debra Graham",
      "type": "Person",
      "genre": null,
      "release_date": null,
      "notable": null,
      "depth": 3
    },
    {
      "id": 14354,
      "name": "Edward Evans",
      "type": "Person",
      "genre": null,
      "release_date": null,
      "notable": null,
      "depth": 3
    },
    {
      "id": 14355,
      "name": "Dylan Schwartz",
      "type": "Person",
      "genre": null,
      "release_date": null,
      "notable": null,
      "depth": 3
    },
    {
      "id": 14356,
      "name": "James Henderson",
      "type": "Person",
      "genre": null,
      "release_date": null,
      "notable": null,
      "depth": 3
    },
    {
      "id": 14357,
      "name": "Amy Powell",
      "type": "Person",
      "genre": null,
      "release_date": null,
      "notable": null,
      "depth": 3
    },
    {
      "id": 14358,
      "name": "Shawn Johnson",
      "type": "Person",
      "genre": null,
      "release_date": null,
      "notable": null,
      "depth": 3
    },
    {
      "id": 14359,
      "name": "Joel Long",
      "type": "Person",
      "genre": null,
      "release_date": null,
      "notable": null,
      "depth": 3
    },
    {
      "id": 14360,
      "name": "Michael Nixon",
      "type": "Person",
      "genre": null,
      "release_date": null,
      "notable": null,
      "depth": 3
    },
    {
      "id": 14361,
      "name": "Nathan Jones",
      "type": "Person",
      "genre": null,
      "release_date": null,
      "notable": null,
      "depth": 3
    },
    {
      "id": 14658,
      "name": "Addicted to Your Heartache",
      "type": "Album",
      "genre": "Southern Gothic Rock",
      "release_date": "2004",
      "notable": true,
      "depth": 2
    },
    {
      "id": 14893,
      "name": "Twilight's Threshold",
      "type": "Song",
      "genre": "Synthwave",
      "release_date": "2007",
      "notable": true,
      "depth": 2
    },
    {
      "id": 14894,
      "name": "Kimberly Estrada",
      "type": "Person",
      "genre": null,
      "release_date": null,
      "notable": null,
      "depth": 3
    },
    {
      "id": 14895,
      "name": "Fang Ding",
      "type": "Person",
      "genre": null,
      "release_date": null,
      "notable": null,
      "depth": 3
    },
    {
      "id": 14933,
      "name": "The Crown We Wear",
      "type": "Song",
      "genre": "Indie Rock",
      "release_date": "2022",
      "notable": true,
      "depth": 2
    },
    {
      "id": 14934,
      "name": "Miss Jennifer Williams",
      "type": "Person",
      "genre": null,
      "release_date": null,
      "notable": null,
      "depth": 3
    },
    {
      "id": 14935,
      "name": "William Robinson",
      "type": "Person",
      "genre": null,
      "release_date": null,
      "notable": null,
      "depth": 3
    },
    {
      "id": 14936,
      "name": "Judy Yang",
      "type": "Person",
      "genre": null,
      "release_date": null,
      "notable": null,
      "depth": 3
    },
    {
      "id": 14937,
      "name": "Joanna Avery",
      "type": "Person",
      "genre": null,
      "release_date": null,
      "notable": null,
      "depth": 3
    },
    {
      "id": 14938,
      "name": "Molly Gonzalez",
      "type": "Person",
      "genre": null,
      "release_date": null,
      "notable": null,
      "depth": 3
    },
    {
      "id": 15224,
      "name": "Juan Shi",
      "type": "Person",
      "genre": null,
      "release_date": null,
      "notable": null,
      "depth": 3
    },
    {
      "id": 15855,
      "name": "Sacred Fragments",
      "type": "Song",
      "genre": "Synthwave",
      "release_date": "2003",
      "notable": true,
      "depth": 2
    },
    {
      "id": 15856,
      "name": "Ming Zhou",
      "type": "Person",
      "genre": null,
      "release_date": null,
      "notable": null,
      "depth": 3
    },
    {
      "id": 16031,
      "name": "Simone S\u00e4uberlich",
      "type": "Person",
      "genre": null,
      "release_date": null,
      "notable": null,
      "depth": 3
    },
    {
      "id": 16312,
      "name": "Harvest Dance at Ler Valley",
      "type": "Song",
      "genre": "Psychedelic Rock",
      "release_date": "2010",
      "notable": true,
      "depth": 2
    },
    {
      "id": 16823,
      "name": "Ursus",
      "type": "MusicalGroup",
      "genre": null,
      "release_date": null,
      "notable": null,
      "depth": 3
    },
    {
      "id": 16910,
      "name": "Phantom Roots",
      "type": "MusicalGroup",
      "genre": null,
      "release_date": null,
      "notable": null,
      "depth": 3
    },
    {
      "id": 16961,
      "name": "Neon Heartbeat",
      "type": "Album",
      "genre": "Synthwave",
      "release_date": "2031",
      "notable": false,
      "depth": 1
    },
    {
      "id": 16989,
      "name": "Ballads for the End of Time",
      "type": "Album",
      "genre": "Oceanus Folk",
      "release_date": "2033",
      "notable": true,
      "depth": 1
    },
    {
      "id": 16999,
      "name": "Melancholy Circuitry",
      "type": "Album",
      "genre": "Americana",
      "release_date": "2033",
      "notable": true,
      "depth": 1
    },
    {
      "id": 17046,
      "name": "The Brine Choir",
      "type": "MusicalGroup",
      "genre": null,
      "release_date": null,
      "notable": null,
      "depth": 2
    },
    {
      "id": 17047,
      "name": "Drifting Between the Stars and the Sea",
      "type": "Album",
      "genre": "Oceanus Folk",
      "release_date": "2034",
      "notable": true,
      "depth": 1
    },
    {
      "id": 17048,
      "name": "Artificial Sunsets",
      "type": "Album",
      "genre": "Oceanus Folk",
      "release_date": "2035",
      "notable": true,
      "depth": 1
    },
    {
      "id": 17049,
      "name": "Electric Reverie",
      "type": "Album",
      "genre": "Oceanus Folk",
      "release_date": "2038",
      "notable": true,
      "depth": 1
    },
    {
      "id": 17121,
      "name": "Ballads for the Low Tide",
      "type": "Album",
      "genre": "Oceanus Folk",
      "release_date": "2037",
      "notable": true,
      "depth": 1
    },
    {
      "id": 17192,
      "name": "The Fiddle & The Fjord",
      "type": "MusicalGroup",
      "genre": null,
      "release_date": null,
      "notable": null,
      "depth": 1
    },
    {
      "id": 17231,
      "name": "Tides of Echos",
      "type": "Album",
      "genre": "Oceanus Folk",
      "release_date": "2029",
      "notable": true,
      "depth": 1
    },
    {
      "id": 17252,
      "name": "Hidden Depths",
      "type": "Album",
      "genre": "Oceanus Folk",
      "release_date": "2031",
      "notable": true,
      "depth": 1
    },
    {
      "id": 17255,
      "name": "Sailor Shift",
      "type": "Person",
      "genre": null,
      "release_date": null,
      "notable": null,
      "depth": 0
    },
    {
      "id": 17260,
      "name": "Ivy Echos",
      "type": "MusicalGroup",
      "genre": null,
      "release_date": null,
      "notable": null,
      "depth": 1
    },
    {
      "id": 17261,
      "name": "The Kelp Forest Canticles",
      "type": "Album",
      "genre": "Oceanus Folk",
      "release_date": "2024",
      "notable": true,
      "depth": 1
    },
    {
      "id": 17262,
      "name": "Luminescent Tides",
      "type": "Album",
      "genre": "Oceanus Folk",
      "release_date": "2025",
      "notable": true,
      "depth": 1
    },
    {
      "id": 17263,
      "name": "Shoreline Sonnets",
      "type": "Album",
      "genre": "Oceanus Folk",
      "release_date": "2026",
      "notable": true,
      "depth": 1
    },
    {
      "id": 17272,
      "name": "Tidal Pop Waves",
      "type": "Album",
      "genre": "Oceanus Folk",
      "release_date": "2028",
      "notable": true,
      "depth": 1
    },
    {
      "id": 17273,
      "name": "Salty Dreams",
      "type": "Album",
      "genre": "Oceanus Folk",
      "release_date": "2030",
      "notable": true,
      "depth": 1
    },
    {
      "id": 17274,
      "name": "The Current & The Chord",
      "type": "Album",
      "genre": "Oceanus Folk",
      "release_date": "2032",
      "notable": true,
      "depth": 1
    },
    {
      "id": 17275,
      "name": "Coral Beats",
      "type": "Album",
      "genre": "Oceanus Folk",
      "release_date": "2034",
      "notable": true,
      "depth": 1
    },
    {
      "id": 17276,
      "name": "Tides & Ballads",
      "type": "Album",
      "genre": "Oceanus Folk",
      "release_date": "2036",
      "notable": true,
      "depth": 1
    },
    {
      "id": 17277,
      "name": "Oceanbound",
      "type": "Album",
      "genre": "Oceanus Folk",
      "release_date": "2038",
      "notable": true,
      "depth": 1
    },
    {
      "id": 17278,
      "name": "Echoes of the Deep",
      "type": "Album",
      "genre": "Oceanus Folk",
      "release_date": "2040",
      "notable": true,
      "depth": 1
    },
    {
      "id": 17279,
      "name": "High Tide Heartbeat",
      "type": "Song",
      "genre": "Oceanus Folk",
      "release_date": "2028",
      "notable": false,
      "depth": 1
    },
    {
      "id": 17280,
      "name": "Electric Eel Love",
      "type": "Song",
      "genre": "Oceanus Folk",
      "release_date": "2028",
      "notable": true,
      "depth": 1
    },
    {
      "id": 17281,
      "name": "Sun-Drenched Daydream",
      "type": "Song",
      "genre": "Oceanus Folk",
      "release_date": "2028",
      "notable": false,
      "depth": 1
    },
    {
      "id": 17282,
      "name": "Chord of the Deep",
      "type": "Song",
      "genre": "Oceanus Folk",
      "release_date": "2028",
      "notable": false,
      "depth": 1
    },
    {
      "id": 17283,
      "name": "Heart of the Habitat",
      "type": "Song",
      "genre": "Oceanus Folk",
      "release_date": "2030",
      "notable": false,
      "depth": 1
    },
    {
      "id": 17284,
      "name": "Reef Rhythm",
      "type": "Song",
      "genre": "Oceanus Folk",
      "release_date": "2030",
      "notable": false,
      "depth": 1
    },
    {
      "id": 17285,
      "name": "Driftwood Lullaby",
      "type": "Song",
      "genre": "Oceanus Folk",
      "release_date": "2030",
      "notable": false,
      "depth": 1
    },
    {
      "id": 17286,
      "name": "Saltwater Hymn",
      "type": "Song",
      "genre": "Oceanus Folk",
      "release_date": "2032",
      "notable": false,
      "depth": 1
    },
    {
      "id": 17287,
      "name": "Moon Over the Tide",
      "type": "Song",
      "genre": "Oceanus Folk",
      "release_date": "2034",
      "notable": true,
      "depth": 1
    },
    {
      "id": 17288,
      "name": "Into the Current",
      "type": "Song",
      "genre": "Oceanus Folk",
      "release_date": "2034",
      "notable": false,
      "depth": 1
    },
    {
      "id": 17289,
      "name": "Barnacle Heart",
      "type": "Song",
      "genre": "Oceanus Folk",
      "release_date": "2034",
      "notable": false,
      "depth": 1
    },
    {
      "id": 17290,
      "name": "Fog & Fiddle",
      "type": "Song",
      "genre": "Oceanus Folk",
      "release_date": "2036",
      "notable": true,
      "depth": 1
    },
    {
      "id": 17291,
      "name": "The Fisherman's Prayer",
      "type": "Song",
      "genre": "Oceanus Folk",
      "release_date": "2036",
      "notable": false,
      "depth": 1
    },
    {
      "id": 17292,
      "name": "Stormsong",
      "type": "Song",
      "genre": "Oceanus Folk",
      "release_date": "2038",
      "notable": true,
      "depth": 1
    },
    {
      "id": 17293,
      "name": "Salt in My Veins",
      "type": "Song",
      "genre": "Oceanus Folk",
      "release_date": "2040",
      "notable": false,
      "depth": 1
    },
    {
      "id": 17294,
      "name": "The Last Mariner",
      "type": "Song",
      "genre": "Oceanus Folk",
      "release_date": "2040",
      "notable": false,
      "depth": 1
    },
    {
      "id": 17299,
      "name": "The Saltwater Weavers",
      "type": "MusicalGroup",
      "genre": null,
      "release_date": null,
      "notable": null,
      "depth": 1
    },
    {
      "id": 17327,
      "name": "Drowned Harbor",
      "type": "MusicalGroup",
      "genre": null,
      "release_date": null,
      "notable": null,
      "depth": 1
    },
    {
      "id": 17350,
      "name": "Tidesworn Ballads",
      "type": "Album",
      "genre": "Oceanus Folk",
      "release_date": "2031",
      "notable": true,
      "depth": 1
    },
    {
      "id": 17356,
      "name": "Submerged Sonatas",
      "type": "Album",
      "genre": "Oceanus Folk",
      "release_date": "2031",
      "notable": true,
      "depth": 1
    },
    {
      "id": 17370,
      "name": "Oceanic Records",
      "type": "RecordLabel",
      "genre": null,
      "release_date": null,
      "notable": null,
      "depth": 2
    },
    {
      "id": 17394,
      "name": "Oceanus Records",
      "type": "RecordLabel",
      "genre": null,
      "release_date": null,
      "notable": null,
      "depth": 2
    },
    {
      "id": 17410,
      "name": "Seashell Serenade",
      "type": "Song",
      "genre": "Oceanus Folk",
      "release_date": "2030",
      "notable": true,
      "depth": 1
    }
  ],
  "edges": [
    {
      "source": 17255,
      "target": 16961,
      "type": "LyricistOf"
    },
    {
      "source": 17255,
      "target": 16989,
      "type": "LyricistOf"
    },
    {
      "source": 17255,
      "target": 16999,
      "type": "LyricistOf"
    },
    {
      "source": 17255,
      "target": 17047,
      "type": "LyricistOf"
    },
    {
      "source": 17255,
      "target": 17048,
      "type": "LyricistOf"
    },
    {
      "source": 17255,
      "target": 17049,
      "type": "LyricistOf"
    },
    {
      "source": 17255,
      "target": 17121,
      "type": "LyricistOf"
    },
    {
      "source": 17255,
      "target": 17231,
      "type": "LyricistOf"
    },
    {
      "source": 17255,
      "target": 17252,
      "type": "LyricistOf"
    },
    {
      "source": 17255,
      "target": 17261,
      "type": "LyricistOf"
    },
    {
      "source": 17255,
      "target": 17262,
      "type": "LyricistOf"
    },
    {
      "source": 17255,
      "target": 17263,
      "type": "LyricistOf"
    },
    {
      "source": 17255,
      "target": 17272,
      "type": "PerformerOf"
    },
    {
      "source": 17255,
      "target": 17272,
      "type": "LyricistOf"
    },
    {
      "source": 17255,
      "target": 17273,
      "type": "PerformerOf"
    },
    {
      "source": 17255,
      "target": 17273,
      "type": "LyricistOf"
    },
    {
      "source": 17255,
      "target": 17274,
      "type": "PerformerOf"
    },
    {
      "source": 17255,
      "target": 17274,
      "type": "LyricistOf"
    },
    {
      "source": 17255,
      "target": 17275,
      "type": "PerformerOf"
    },
    {
      "source": 17255,
      "target": 17275,
      "type": "LyricistOf"
    },
    {
      "source": 17255,
      "target": 17276,
      "type": "PerformerOf"
    },
    {
      "source": 17255,
      "target": 17276,
      "type": "LyricistOf"
    },
    {
      "source": 17255,
      "target": 17277,
      "type": "PerformerOf"
    },
    {
      "source": 17255,
      "target": 17277,
      "type": "LyricistOf"
    },
    {
      "source": 17255,
      "target": 17278,
      "type": "PerformerOf"
    },
    {
      "source": 17255,
      "target": 17278,
      "type": "LyricistOf"
    },
    {
      "source": 17255,
      "target": 17279,
      "type": "PerformerOf"
    },
    {
      "source": 17255,
      "target": 17280,
      "type": "PerformerOf"
    },
    {
      "source": 17255,
      "target": 17281,
      "type": "PerformerOf"
    },
    {
      "source": 17255,
      "target": 17282,
      "type": "PerformerOf"
    },
    {
      "source": 17255,
      "target": 17283,
      "type": "PerformerOf"
    },
    {
      "source": 17255,
      "target": 17284,
      "type": "PerformerOf"
    },
    {
      "source": 17255,
      "target": 17285,
      "type": "PerformerOf"
    },
    {
      "source": 17255,
      "target": 17286,
      "type": "PerformerOf"
    },
    {
      "source": 17255,
      "target": 17287,
      "type": "PerformerOf"
    },
    {
      "source": 17255,
      "target": 17288,
      "type": "PerformerOf"
    },
    {
      "source": 17255,
      "target": 17289,
      "type": "PerformerOf"
    },
    {
      "source": 17255,
      "target": 17290,
      "type": "PerformerOf"
    },
    {
      "source": 17255,
      "target": 17291,
      "type": "PerformerOf"
    },
    {
      "source": 17255,
      "target": 17292,
      "type": "PerformerOf"
    },
    {
      "source": 17255,
      "target": 17293,
      "type": "PerformerOf"
    },
    {
      "source": 17255,
      "target": 17294,
      "type": "PerformerOf"
    },
    {
      "source": 17255,
      "target": 17350,
      "type": "LyricistOf"
    },
    {
      "source": 17255,
      "target": 17350,
      "type": "PerformerOf"
    },
    {
      "source": 17255,
      "target": 17356,
      "type": "LyricistOf"
    },
    {
      "source": 17255,
      "target": 17356,
      "type": "PerformerOf"
    },
    {
      "source": 17255,
      "target": 17410,
      "type": "PerformerOf"
    },
    {
      "source": 17255,
      "target": 17260,
      "type": "DirectlySamples"
    },
    {
      "source": 17255,
      "target": 17299,
      "type": "InStyleOf"
    },
    {
      "source": 17255,
      "target": 17327,
      "type": "LyricalReferenceTo"
    },
    {
      "source": 17255,
      "target": 17192,
      "type": "InStyleOf"
    },
    {
      "source": 16999,
      "target": 14893,
      "type": "CoverOf"
    },
    {
      "source": 17049,
      "target": 14107,
      "type": "InStyleOf"
    },
    {
      "source": 17049,
      "target": 7026,
      "type": "InterpolatesFrom"
    },
    {
      "source": 17231,
      "target": 14352,
      "type": "InterpolatesFrom"
    },
    {
      "source": 17231,
      "target": 14296,
      "type": "InStyleOf"
    },
    {
      "source": 17261,
      "target": 2197,
      "type": "DirectlySamples"
    },
    {
      "source": 17261,
      "target": 9223,
      "type": "CoverOf"
    },
    {
      "source": 17273,
      "target": 3881,
      "type": "InStyleOf"
    },
    {
      "source": 17273,
      "target": 9848,
      "type": "CoverOf"
    },
    {
      "source": 17275,
      "target": 16312,
      "type": "CoverOf"
    },
    {
      "source": 17275,
      "target": 15855,
      "type": "InStyleOf"
    },
    {
      "source": 17277,
      "target": 876,
      "type": "LyricalReferenceTo"
    },
    {
      "source": 17277,
      "target": 3986,
      "type": "LyricalReferenceTo"
    },
    {
      "source": 17279,
      "target": 14658,
      "type": "InterpolatesFrom"
    },
    {
      "source": 17280,
      "target": 14933,
      "type": "CoverOf"
    },
    {
      "source": 17280,
      "target": 10534,
      "type": "InStyleOf"
    },
    {
      "source": 17285,
      "target": 8207,
      "type": "InStyleOf"
    },
    {
      "source": 17286,
      "target": 10903,
      "type": "InStyleOf"
    },
    {
      "source": 17287,
      "target": 13589,
      "type": "LyricalReferenceTo"
    },
    {
      "source": 17287,
      "target": 11254,
      "type": "InterpolatesFrom"
    },
    {
      "source": 17289,
      "target": 5574,
      "type": "InStyleOf"
    },
    {
      "source": 17290,
      "target": 12685,
      "type": "InterpolatesFrom"
    },
    {
      "source": 17290,
      "target": 12237,
      "type": "InStyleOf"
    },
    {
      "source": 17292,
      "target": 13014,
      "type": "DirectlySamples"
    },
    {
      "source": 17292,
      "target": 6592,
      "type": "InStyleOf"
    },
    {
      "source": 17350,
      "target": 10016,
      "type": "CoverOf"
    },
    {
      "source": 9224,
      "target": 9223,
      "type": "PerformerOf"
    },
    {
      "source": 9225,
      "target": 9223,
      "type": "PerformerOf"
    },
    {
      "source": 9226,
      "target": 9223,
      "type": "PerformerOf"
    },
    {
      "source": 9227,
      "target": 9223,
      "type": "LyricistOf"
    },
    {
      "source": 9228,
      "target": 9223,
      "type": "PerformerOf"
    },
    {
      "source": 12686,
      "target": 12685,
      "type": "PerformerOf"
    },
    {
      "source": 12687,
      "target": 12685,
      "type": "LyricistOf"
    },
    {
      "source": 12687,
      "target": 12685,
      "type": "PerformerOf"
    },
    {
      "source": 12688,
      "target": 12685,
      "type": "PerformerOf"
    },
    {
      "source": 8208,
      "target": 8207,
      "type": "PerformerOf"
    },
    {
      "source": 8208,
      "target": 8207,
      "type": "LyricistOf"
    },
    {
      "source": 14353,
      "target": 14352,
      "type": "ComposerOf"
    },
    {
      "source": 14353,
      "target": 14352,
      "type": "PerformerOf"
    },
    {
      "source": 14354,
      "target": 14352,
      "type": "LyricistOf"
    },
    {
      "source": 14355,
      "target": 14352,
      "type": "PerformerOf"
    },
    {
      "source": 14356,
      "target": 14352,
      "type": "PerformerOf"
    },
    {
      "source": 14357,
      "target": 14352,
      "type": "ProducerOf"
    },
    {
      "source": 14358,
      "target": 14352,
      "type": "ProducerOf"
    },
    {
      "source": 14359,
      "target": 14352,
      "type": "PerformerOf"
    },
    {
      "source": 14360,
      "target": 14352,
      "type": "ComposerOf"
    },
    {
      "source": 14360,
      "target": 14352,
      "type": "PerformerOf"
    },
    {
      "source": 14361,
      "target": 14352,
      "type": "PerformerOf"
    },
    {
      "source": 1276,
      "target": 3986,
      "type": "PerformerOf"
    },
    {
      "source": 2400,
      "target": 3986,
      "type": "ComposerOf"
    },
    {
      "source": 3987,
      "target": 3986,
      "type": "PerformerOf"
    },
    {
      "source": 3988,
      "target": 3986,
      "type": "ComposerOf"
    },
    {
      "source": 3988,
      "target": 3986,
      "type": "PerformerOf"
    },
    {
      "source": 3989,
      "target": 3986,
      "type": "PerformerOf"
    },
    {
      "source": 3990,
      "target": 3986,
      "type": "PerformerOf"
    },
    {
      "source": 17046,
      "target": 17299,
      "type": "LyricistOf"
    },
    {
      "source": 17370,
      "target": 17299,
      "type": "ProducerOf"
    },
    {
      "source": 2198,
      "target": 2197,
      "type": "ProducerOf"
    },
    {
      "source": 2199,
      "target": 2197,
      "type": "ComposerOf"
    },
    {
      "source": 2200,
      "target": 2197,
      "type": "LyricistOf"
    },
    {
      "source": 2200,
      "target": 2197,
      "type": "PerformerOf"
    },
    {
      "source": 8880,
      "target": 13589,
      "type": "PerformerOf"
    },
    {
      "source": 8880,
      "target": 13589,
      "type": "ProducerOf"
    },
    {
      "source": 13590,
      "target": 13589,
      "type": "ComposerOf"
    },
    {
      "source": 10904,
      "target": 10903,
      "type": "LyricistOf"
    },
    {
      "source": 10905,
      "target": 10903,
      "type": "PerformerOf"
    },
    {
      "source": 10905,
      "target": 10903,
      "type": "ProducerOf"
    },
    {
      "source": 10906,
      "target": 10903,
      "type": "PerformerOf"
    },
    {
      "source": 10907,
      "target": 10903,
      "type": "PerformerOf"
    },
    {
      "source": 10908,
      "target": 10903,
      "type": "ComposerOf"
    },
    {
      "source": 10908,
      "target": 10903,
      "type": "PerformerOf"
    },
    {
      "source": 12948,
      "target": 14107,
      "type": "PerformerOf"
    },
    {
      "source": 14108,
      "target": 14107,
      "type": "ComposerOf"
    },
    {
      "source": 14108,
      "target": 14107,
      "type": "PerformerOf"
    },
    {
      "source": 10017,
      "target": 10016,
      "type": "LyricistOf"
    },
    {
      "source": 10018,
      "target": 10016,
      "type": "PerformerOf"
    },
    {
      "source": 10019,
      "target": 10016,
      "type": "PerformerOf"
    },
    {
      "source": 10020,
      "target": 10016,
      "type": "PerformerOf"
    },
    {
      "source": 10021,
      "target": 10016,
      "type": "PerformerOf"
    },
    {
      "source": 10022,
      "target": 10016,
      "type": "ComposerOf"
    },
    {
      "source": 10022,
      "target": 10016,
      "type": "PerformerOf"
    },
    {
      "source": 2705,
      "target": 10534,
      "type": "PerformerOf"
    },
    {
      "source": 2705,
      "target": 10534,
      "type": "ProducerOf"
    },
    {
      "source": 2706,
      "target": 10534,
      "type": "PerformerOf"
    },
    {
      "source": 2707,
      "target": 10534,
      "type": "LyricistOf"
    },
    {
      "source": 2707,
      "target": 10534,
      "type": "PerformerOf"
    },
    {
      "source": 17394,
      "target": 17192,
      "type": "ProducerOf"
    },
    {
      "source": 934,
      "target": 3881,
      "type": "PerformerOf"
    },
    {
      "source": 3760,
      "target": 3881,
      "type": "LyricistOf"
    },
    {
      "source": 3760,
      "target": 3881,
      "type": "PerformerOf"
    },
    {
      "source": 3761,
      "target": 3881,
      "type": "LyricistOf"
    },
    {
      "source": 3761,
      "target": 3881,
      "type": "PerformerOf"
    },
    {
      "source": 3763,
      "target": 3881,
      "type": "PerformerOf"
    },
    {
      "source": 3764,
      "target": 3881,
      "type": "ProducerOf"
    },
    {
      "source": 3882,
      "target": 3881,
      "type": "PerformerOf"
    },
    {
      "source": 3883,
      "target": 3881,
      "type": "PerformerOf"
    },
    {
      "source": 16823,
      "target": 3881,
      "type": "PerformerOf"
    },
    {
      "source": 1335,
      "target": 14893,
      "type": "PerformerOf"
    },
    {
      "source": 1335,
      "target": 14893,
      "type": "ProducerOf"
    },
    {
      "source": 1336,
      "target": 14893,
      "type": "LyricistOf"
    },
    {
      "source": 14894,
      "target": 14893,
      "type": "PerformerOf"
    },
    {
      "source": 14895,
      "target": 14893,
      "type": "PerformerOf"
    },
    {
      "source": 16910,
      "target": 14893,
      "type": "PerformerOf"
    },
    {
      "source": 17370,
      "target": 17327,
      "type": "ProducerOf"
    },
    {
      "source": 304,
      "target": 16312,
      "type": "ProducerOf"
    },
    {
      "source": 16031,
      "target": 16312,
      "type": "ComposerOf"
    },
    {
      "source": 16031,
      "target": 16312,
      "type": "PerformerOf"
    },
    {
      "source": 6593,
      "target": 6592,
      "type": "PerformerOf"
    },
    {
      "source": 6593,
      "target": 6592,
      "type": "LyricistOf"
    },
    {
      "source": 1294,
      "target": 14658,
      "type": "PerformerOf"
    },
    {
      "source": 1294,
      "target": 14658,
      "type": "LyricistOf"
    },
    {
      "source": 1294,
      "target": 14658,
      "type": "ComposerOf"
    },
    {
      "source": 5575,
      "target": 5574,
      "type": "PerformerOf"
    },
    {
      "source": 5575,
      "target": 5574,
      "type": "LyricistOf"
    },
    {
      "source": 5575,
      "target": 5574,
      "type": "ComposerOf"
    },
    {
      "source": 76,
      "target": 12237,
      "type": "PerformerOf"
    },
    {
      "source": 12238,
      "target": 12237,
      "type": "PerformerOf"
    },
    {
      "source": 12238,
      "target": 12237,
      "type": "ProducerOf"
    },
    {
      "source": 12239,
      "target": 12237,
      "type": "LyricistOf"
    },
    {
      "source": 12239,
      "target": 12237,
      "type": "PerformerOf"
    },
    {
      "source": 12240,
      "target": 12237,
      "type": "PerformerOf"
    },
    {
      "source": 12241,
      "target": 12237,
      "type": "PerformerOf"
    },
    {
      "source": 14934,
      "target": 14933,
      "type": "PerformerOf"
    },
    {
      "source": 14935,
      "target": 14933,
      "type": "PerformerOf"
    },
    {
      "source": 14935,
      "target": 14933,
      "type": "ProducerOf"
    },
    {
      "source": 14936,
      "target": 14933,
      "type": "PerformerOf"
    },
    {
      "source": 14937,
      "target": 14933,
      "type": "PerformerOf"
    },
    {
      "source": 14938,
      "target": 14933,
      "type": "PerformerOf"
    },
    {
      "source": 8026,
      "target": 13014,
      "type": "ComposerOf"
    },
    {
      "source": 13015,
      "target": 13014,
      "type": "PerformerOf"
    },
    {
      "source": 13016,
      "target": 13014,
      "type": "PerformerOf"
    },
    {
      "source": 13017,
      "target": 13014,
      "type": "PerformerOf"
    },
    {
      "source": 13018,
      "target": 13014,
      "type": "PerformerOf"
    },
    {
      "source": 14297,
      "target": 14296,
      "type": "LyricistOf"
    },
    {
      "source": 14298,
      "target": 14296,
      "type": "PerformerOf"
    },
    {
      "source": 14298,
      "target": 14296,
      "type": "ProducerOf"
    },
    {
      "source": 17370,
      "target": 17260,
      "type": "ProducerOf"
    },
    {
      "source": 877,
      "target": 876,
      "type": "ComposerOf"
    },
    {
      "source": 878,
      "target": 876,
      "type": "PerformerOf"
    },
    {
      "source": 878,
      "target": 876,
      "type": "ProducerOf"
    },
    {
      "source": 455,
      "target": 15855,
      "type": "PerformerOf"
    },
    {
      "source": 455,
      "target": 15855,
      "type": "ProducerOf"
    },
    {
      "source": 457,
      "target": 15855,
      "type": "PerformerOf"
    },
    {
      "source": 1952,
      "target": 15855,
      "type": "ComposerOf"
    },
    {
      "source": 15224,
      "target": 15855,
      "type": "PerformerOf"
    },
    {
      "source": 15856,
      "target": 15855,
      "type": "PerformerOf"
    },
    {
      "source": 7027,
      "target": 7026,
      "type": "PerformerOf"
    },
    {
      "source": 7028,
      "target": 7026,
      "type": "ComposerOf"
    },
    {
      "source": 7029,
      "target": 7026,
      "type": "PerformerOf"
    },
    {
      "source": 7030,
      "target": 7026,
      "type": "ProducerOf"
    },
    {
      "source": 11255,
      "target": 11254,
      "type": "PerformerOf"
    },
    {
      "source": 11255,
      "target": 11254,
      "type": "LyricistOf"
    },
    {
      "source": 11255,
      "target": 11254,
      "type": "ComposerOf"
    },
    {
      "source": 3086,
      "target": 9848,
      "type": "ProducerOf"
    },
    {
      "source": 5213,
      "target": 9848,
      "type": "PerformerOf"
    }
  ]
}